localDataBaseFolder/__init__.py
localDataBase-1.0.dist-info/LICENSE
localDataBase-1.0.dist-info/METADATA
localDataBase-1.0.dist-info/WHEEL
localDataBase-1.0.dist-info/top_level.txt
localDataBase-1.0.dist-info/RECORD
