Metadata-Version: 2.1
Name: localDataBase
Version: 1.0
Summary: localDB is a Python package that allows you to generate a local database in the file system. With localDB, users can create, update, delete, and search a local database on their system. This package can be useful for applications that reire a simple and efficient local data storage solution. Additionally, being a local database solution, it does not require an internet connection or depend on external services.
Author-email: Thiago Stilo <stilothiagovalentin@gmail.com>
Project-URL: Homepage, https://github.com/thiagostilo2121/localDB-python
Project-URL: Bug Tracker, https://github.com/thiagostilo2121/localDB-python/issues
Classifier: Programming Language :: Python :: 3
Classifier: License :: OSI Approved :: MIT License
Classifier: Operating System :: OS Independent
Requires-Python: >=3.9
License-File: LICENSE
